stserve/__init__.py
stserve/app.py
stserve-0.1.0.dist-info/METADATA
stserve-0.1.0.dist-info/WHEEL
stserve-0.1.0.dist-info/entry_points.txt
stserve-0.1.0.dist-info/RECORD
