Metadata-Version: 2.4
Name: stserve
Version: 0.1.0
Summary: Light-weight server exposing sentence-transformer models for embeddings
Requires-Python: >=3.13
Requires-Dist: click>=8.1.7
Requires-Dist: fastapi>=0.118.2
Requires-Dist: sentence-transformers>=5.1.1
Requires-Dist: uvicorn>=0.37.0
